book/__init__.py
book/admin.py
book/apps.py
book/models.py
django_book-0.1.1.dist-info/AUTHORS.rst
django_book-0.1.1.dist-info/METADATA
django_book-0.1.1.dist-info/WHEEL
django_book-0.1.1.dist-info/top_level.txt
django_book-0.1.1.dist-info/RECORD
