Metadata-Version: 2.1
Name: django-book
Version: 0.1.1
Summary: Django app for storing books and pages
Home-page: https://gitlab.com/reedrichards/book
Author: Robert Wendt
Author-email: rwendt1337@gmail.com
License: UNKNOWN
Keywords: book
Platform: UNKNOWN
Classifier: Development Status :: 2 - Pre-Alpha
Classifier: Intended Audience :: Developers
Classifier: Natural Language :: English
Classifier: Programming Language :: Python :: 3
Classifier: Programming Language :: Python :: 3.6
Classifier: Programming Language :: Python :: 3.7
Requires-Python: >=3.6
Requires-Dist: django
Requires-Dist: pillow
